Orange3_Azure_Data_Lake_Storage_Gen2-0.0.1-py3.11-nspkg.pth
orangecontrib/adls/__init__.py
orangecontrib/adls/widgets/__init__.py
orangecontrib/adls/widgets/azure_utils.py
orangecontrib/adls/widgets/owadlsload.py
orangecontrib/adls/widgets/owadlssave.py
orangecontrib/adls/widgets/icons/adls.svg
orangecontrib/adls/widgets/icons/adls_load.svg
orangecontrib/adls/widgets/icons/adls_save.svg
Orange3_Azure_Data_Lake_Storage_Gen2-0.0.1.dist-info/METADATA
Orange3_Azure_Data_Lake_Storage_Gen2-0.0.1.dist-info/WHEEL
Orange3_Azure_Data_Lake_Storage_Gen2-0.0.1.dist-info/entry_points.txt
Orange3_Azure_Data_Lake_Storage_Gen2-0.0.1.dist-info/namespace_packages.txt
Orange3_Azure_Data_Lake_Storage_Gen2-0.0.1.dist-info/top_level.txt
Orange3_Azure_Data_Lake_Storage_Gen2-0.0.1.dist-info/RECORD
